bin/build.sh
config/latest-mt-debug-howso.yml
config/latest-mt-howso.yml
config/latest-mt-noavx-debug-howso.yml
config/latest-st-debug-howso.yml
config/latest-st-howso.yml
config/powershell/Download-Tzdata.ps1
config/powershell/Helper-Functions.ps1
howso/visuals/__init__.py
howso/visuals/colors.py
howso/visuals/graph.py
howso/visuals/visuals.py
howso/visuals/data/iris.csv
howso/visuals/tests/conftest.py
howso/visuals/tests/test_graph.py
howso/visuals/tests/test_plot.py
howso_visuals-3.0.4.dist-info/licenses/LICENSE-3RD-PARTY.txt
howso_visuals-3.0.4.dist-info/licenses/LICENSE.txt
howso_visuals-3.0.4.dist-info/METADATA
howso_visuals-3.0.4.dist-info/WHEEL
howso_visuals-3.0.4.dist-info/top_level.txt
howso_visuals-3.0.4.dist-info/RECORD
