Metadata-Version: 2.4
Name: howso-visuals
Version: 3.0.4
Summary: Visualization utilities for use with Howso Engine.
License: GNU AFFERO GENERAL PUBLIC LICENSE
Project-URL: homepage, https://howso.com
Project-URL: documentation, https://docs.howso.com/
Project-URL: repository, https://github.com/howsoai/howso-visuals-py
Keywords: machine,learning,artificial,intelligence,data,visualization
Classifier: Development Status :: 3 - Alpha
Classifier: License :: OSI Approved :: GNU Affero General Public License v3
Classifier: Programming Language :: Python :: 3
Requires-Python: >=3.10
License-File: LICENSE-3RD-PARTY.txt
License-File: LICENSE.txt
Requires-Dist: howso-engine>=51.0
Requires-Dist: networkx
Requires-Dist: plotly[kaleido]~=6.0
Requires-Dist: scipy
Requires-Dist: seaborn
Requires-Dist: umap-learn~=0.5
Provides-Extra: dev
Requires-Dist: flake8; extra == "dev"
Requires-Dist: isort; extra == "dev"
Requires-Dist: pytest-cov; extra == "dev"
Requires-Dist: pytest-rerunfailures; extra == "dev"
Requires-Dist: pytest-xdist; extra == "dev"
Requires-Dist: pytest; extra == "dev"
Requires-Dist: ruff; extra == "dev"
Requires-Dist: yapf; extra == "dev"
Dynamic: license-file
